MiTM/__init__.py
MiTM/history.py
MiTM/AnomalyObjects/AbstractAnomalyObjectFile.py
MiTM/AnomalyObjects/__init__.py
MiTM/AnomalyObjects/Action/AbstractActionFile.py
MiTM/AnomalyObjects/Action/AddWhiteNoiseFile.py
MiTM/AnomalyObjects/Action/AvgSensorsFile.py
MiTM/AnomalyObjects/Action/DisconnectSensorFile.py
MiTM/AnomalyObjects/Action/DummyAction.py
MiTM/AnomalyObjects/Action/DuplicateFile.py
MiTM/AnomalyObjects/Action/RandomChangeFile.py
MiTM/AnomalyObjects/Action/__init__.py
MiTM/AnomalyObjects/Condition/AbstractConditionFile.py
MiTM/AnomalyObjects/Condition/EndTime.py
MiTM/AnomalyObjects/Condition/GetToIterationFile.py
MiTM/AnomalyObjects/Condition/GetToTimestampFile.py
MiTM/AnomalyObjects/Condition/RandomStart.py
MiTM/AnomalyObjects/Condition/__init__.py
MiTM/AnomalyObjects/Listener/AbstractListenerFile.py
MiTM/AnomalyObjects/Listener/ListenerFile.py
MiTM/AnomalyObjects/Listener/__init__.py
MiTM/Scenario/BaseScenario.py
MiTM/Scenario/OneSensorScenario.py
MiTM/Scenario/__init__.py
SCART/__init__.py
SCART/history.py
SCART/AnomalyObjects/AbstractAnomalyObjectFile.py
SCART/AnomalyObjects/__init__.py
SCART/AnomalyObjects/Action/AbstractActionFile.py
SCART/AnomalyObjects/Action/AddWhiteNoiseFile.py
SCART/AnomalyObjects/Action/AvgSensorsFile.py
SCART/AnomalyObjects/Action/DisconnectSensorFile.py
SCART/AnomalyObjects/Action/DummyAction.py
SCART/AnomalyObjects/Action/DuplicateFile.py
SCART/AnomalyObjects/Action/RandomChangeFile.py
SCART/AnomalyObjects/Action/__init__.py
SCART/AnomalyObjects/Condition/AbstractConditionFile.py
SCART/AnomalyObjects/Condition/EndTime.py
SCART/AnomalyObjects/Condition/GetToIterationFile.py
SCART/AnomalyObjects/Condition/GetToTimestampFile.py
SCART/AnomalyObjects/Condition/RandomStart.py
SCART/AnomalyObjects/Condition/__init__.py
SCART/AnomalyObjects/Listener/AbstractListenerFile.py
SCART/AnomalyObjects/Listener/ListenerFile.py
SCART/AnomalyObjects/Listener/__init__.py
SCART/Scenario/BaseScenario.py
SCART/Scenario/OneSensorScenario.py
scart-1.0.0.dist-info/LICENSE
scart-1.0.0.dist-info/METADATA
scart-1.0.0.dist-info/WHEEL
scart-1.0.0.dist-info/entry_points.txt
scart-1.0.0.dist-info/top_level.txt
scart-1.0.0.dist-info/RECORD
