Metadata-Version: 1.0
Name: scart
Version: 1.0.0
Summary: scart is a tool to generate MITM scripts for network attacks
Home-page: https://github.com/kfirgirstein/scart
Author: Kfir Girstein
Author-email: UNKNOWN
License: UNKNOWN
Platform: UNKNOWN
